{
	"format_version": "1.8.0",
	"animations": {
		"animation.cat.fly": {
			"animation_length": 0.75,
			"bones": {
				"bone": {
					"rotation": {
						"0.0": {
							"post": [0, 0, 0],
							"lerp_mode": "catmullrom"
						},
						"0.125": {
							"post": [0, -52.5, 0],
							"lerp_mode": "catmullrom"
						},
						"0.2917": {
							"post": [0, 22.5, 0],
							"lerp_mode": "catmullrom"
						},
						"0.5": {
							"post": [0, 0, 0],
							"lerp_mode": "catmullrom"
						}
					}
				},
				"bone4": {
					"rotation": {
						"0.0": {
							"post": [0, 0, 0],
							"lerp_mode": "catmullrom"
						},
						"0.125": {
							"post": [0, 52.5, 0],
							"lerp_mode": "catmullrom"
						},
						"0.2917": {
							"post": [0, -22.5, 0],
							"lerp_mode": "catmullrom"
						},
						"0.5": {
							"post": [0, 0, 0],
							"lerp_mode": "catmullrom"
						}
					}
				}
			}
		}
	}
}